todoist_mcp_server/__init__.py
todoist_mcp_server/todoist.py
todoist_mcp_server/todoist_client.py
todoist_mcp_server-0.1.3.dist-info/METADATA
todoist_mcp_server-0.1.3.dist-info/WHEEL
todoist_mcp_server-0.1.3.dist-info/entry_points.txt
todoist_mcp_server-0.1.3.dist-info/licenses/LICENSE
todoist_mcp_server-0.1.3.dist-info/RECORD
