Metadata-Version: 2.4
Name: todoist-mcp-server
Version: 0.1.3
Summary: MCP Server for Todoist task management
Project-URL: Homepage, https://github.com/mehularora8/todoist-mcp
Project-URL: Repository, https://github.com/mehularora8/todoist-mcp
Project-URL: Issues, https://github.com/mehularora8/todoist-mcp/issues
Author-email: Mehul Arora <aroramehul8@gmail.com>
License: MIT
License-File: LICENSE
Keywords: mcp,productivity,task-management,todoist
Classifier: Development Status :: 3 - Alpha
Classifier: Intended Audience :: Developers
Classifier: License :: OSI Approved :: MIT License
Classifier: Programming Language :: Python :: 3
Classifier: Programming Language :: Python :: 3.12
Requires-Python: >=3.12
Requires-Dist: httpx>=0.28.1
Requires-Dist: mcp[cli]>=1.10.1
